assetuniverse/__init__.py
assetuniverse/core.py
assetuniverse/utils/__init__.py
assetuniverse/utils/asset.py
assetuniverse/utils/downloaders.py
assetuniverse-0.1.1.dist-info/LICENSE
assetuniverse-0.1.1.dist-info/METADATA
assetuniverse-0.1.1.dist-info/WHEEL
assetuniverse-0.1.1.dist-info/top_level.txt
assetuniverse-0.1.1.dist-info/RECORD
