Metadata-Version: 2.1
Name: assetuniverse
Version: 0.1.1
Summary: A downloader of historical daily returns for multiple investable assets with some analysis tools too.
Author: Matthew Trotter
License: GPL-3.0-or-later
Keywords: historical returns,returns,daily returns,stocks,futures,commodities,interactive brokers,yahoo finance,fred
Classifier: Programming Language :: Python :: 3
Classifier: License :: OSI Approved :: GNU General Public License v3 (GPLv3)
Classifier: Operating System :: OS Independent
Requires-Python: >=3.7
License-File: LICENSE
Requires-Dist: appdirs
Requires-Dist: diskcache
Requires-Dist: ib-insync
Requires-Dist: numpy
Requires-Dist: pandas
Requires-Dist: pandas-datareader
Requires-Dist: plotly
Requires-Dist: yfinance
